invenio_sequencegenerator/__init__.py
invenio_sequencegenerator/admin.py
invenio_sequencegenerator/api.py
invenio_sequencegenerator/cli.py
invenio_sequencegenerator/errors.py
invenio_sequencegenerator/ext.py
invenio_sequencegenerator/models.py
invenio_sequencegenerator/utils.py
invenio_sequencegenerator/version.py
invenio_sequencegenerator/templates/invenio_sequencegenerator/custom_list.html
invenio_sequencegenerator/translations/invenio.pot
invenio_sequencegenerator/translations/de/LC_MESSAGES/messages.mo
invenio_sequencegenerator/translations/de/LC_MESSAGES/messages.po
invenio_sequencegenerator/translations/es/LC_MESSAGES/messages.mo
invenio_sequencegenerator/translations/es/LC_MESSAGES/messages.po
invenio_sequencegenerator/translations/fr/LC_MESSAGES/messages.mo
invenio_sequencegenerator/translations/fr/LC_MESSAGES/messages.po
invenio_sequencegenerator/translations/it/LC_MESSAGES/messages.mo
invenio_sequencegenerator/translations/it/LC_MESSAGES/messages.po
invenio_sequencegenerator-1.0.0a3.dist-info/AUTHORS.rst
invenio_sequencegenerator-1.0.0a3.dist-info/LICENSE
invenio_sequencegenerator-1.0.0a3.dist-info/METADATA
invenio_sequencegenerator-1.0.0a3.dist-info/WHEEL
invenio_sequencegenerator-1.0.0a3.dist-info/entry_points.txt
invenio_sequencegenerator-1.0.0a3.dist-info/top_level.txt
invenio_sequencegenerator-1.0.0a3.dist-info/RECORD
