Metadata-Version: 2.1
Name: invenio-sequencegenerator
Version: 1.0.0a3
Summary: Invenio module for generating sequences.
Home-page: https://github.com/inveniosoftware/invenio-sequencegenerator
Author: CERN
Author-email: info@inveniosoftware.org
License: MIT
Keywords: invenio minter pidstore autoincrement
Platform: any
Classifier: Environment :: Web Environment
Classifier: Intended Audience :: Developers
Classifier: License :: OSI Approved :: MIT License
Classifier: Operating System :: OS Independent
Classifier: Programming Language :: Python
Classifier: Topic :: Internet :: WWW/HTTP :: Dynamic Content
Classifier: Topic :: Software Development :: Libraries :: Python Modules
Classifier: Programming Language :: Python :: 2
Classifier: Programming Language :: Python :: 2.7
Classifier: Programming Language :: Python :: 3
Classifier: Programming Language :: Python :: 3.5
Classifier: Development Status :: 4 - Beta
Requires-Dist: sqlalchemy-utils >=0.31
Requires-Dist: invenio-admin >=1.0.0
Requires-Dist: invenio-base >=1.2.0
Requires-Dist: invenio-db >=1.0.0
Requires-Dist: invenio-i18n >=2.0.0
Provides-Extra: admin
Requires-Dist: Flask-Admin >=1.5.6 ; extra == 'admin'
Provides-Extra: all
Requires-Dist: Sphinx >=3 ; extra == 'all'
Requires-Dist: Flask-Admin >=1.5.6 ; extra == 'all'
Requires-Dist: pytest-invenio >=1.4.0 ; extra == 'all'
Provides-Extra: docs
Requires-Dist: Sphinx >=3 ; extra == 'docs'
Provides-Extra: mysql
Requires-Dist: invenio-db[mysql,versioning] >=1.0.0 ; extra == 'mysql'
Provides-Extra: postgresql
Requires-Dist: invenio-db[postgresql,versioning] >=1.0.0 ; extra == 'postgresql'
Provides-Extra: sqlite
Requires-Dist: invenio-db[versioning] >=1.0.0 ; extra == 'sqlite'
Provides-Extra: tests
Requires-Dist: pytest-invenio >=1.4.0 ; extra == 'tests'
